zerorvc/__init__.py
zerorvc/auto_loader.py
zerorvc/constants.py
zerorvc/dataset.py
zerorvc/pretrained.py
zerorvc/rvc.py
zerorvc/trainer.py
zerorvc/assets/mute/mute48k.wav
zerorvc/f0/__init__.py
zerorvc/f0/extractor.py
zerorvc/f0/load.py
zerorvc/f0/rmvpe/__init__.py
zerorvc/f0/rmvpe/constants.py
zerorvc/f0/rmvpe/deepunet.py
zerorvc/f0/rmvpe/mel.py
zerorvc/f0/rmvpe/model.py
zerorvc/f0/rmvpe/seq.py
zerorvc/hubert/__init__.py
zerorvc/hubert/extractor.py
zerorvc/hubert/load.py
zerorvc/preprocess/__init__.py
zerorvc/preprocess/crop.py
zerorvc/preprocess/preprocess.py
zerorvc/preprocess/slicer2.py
zerorvc/synthesizer/__init__.py
zerorvc/synthesizer/attentions.py
zerorvc/synthesizer/commons.py
zerorvc/synthesizer/models.py
zerorvc/synthesizer/modules.py
zerorvc/synthesizer/transforms.py
zerorvc/utils/__init__.py
zerorvc/utils/data_utils.py
zerorvc/utils/losses.py
zerorvc/utils/mel_processing.py
zerorvc-0.0.19.dist-info/METADATA
zerorvc-0.0.19.dist-info/WHEEL
zerorvc-0.0.19.dist-info/licenses/LICENSE
zerorvc-0.0.19.dist-info/RECORD
